serial.py
setup.py
micropython_serial.egg-info/PKG-INFO
micropython_serial.egg-info/SOURCES.txt
micropython_serial.egg-info/dependency_links.txt
micropython_serial.egg-info/requires.txt
micropython_serial.egg-info/top_level.txt