Metadata-Version: 1.0
Name: micropython-serial
Version: 0.1
Summary: pySerial-like module for MicroPython (unix port).
Home-page: https://github.com/pfalcon/micropython-serial
Author: Paul Sokolovsky
Author-email: pfalcon@users.sourceforge.net
License: MIT
Platform: UNKNOWN
